{
  "title": "Understanding InfiniCode: A Next-Generation IDE",
  "description": "Explore InfiniCode, an innovative IDE that bridges the gap between visual and code editing through real-time WYSIWYG capabilities.",
  "author": "Martin Ouimet",
  "date": "2024-03-31",
  "order": 1,
  "seriesSlug": "infinicode-series",
  "slug": "understanding-infinicode",
  "tags": [
    "IDE",
    "WYSIWYG",
    "TypeScript",
    "React",
    "VS Code",
    "WebSocket"
  ],
  "category": "Development Tools",
  "githubRepo": "",
  "status": "draft",
  "publishDate": "2025-04-05"
}